argus_temporal_logic-0.1.4.dist-info/METADATA
argus_temporal_logic-0.1.4.dist-info/WHEEL
argus/test_utils/signals_gen.py
argus/test_utils/__init__.py
argus/test_utils/expr_gen.py
argus/__init__.py
argus/_argus.pyi
argus/py.typed
argus/__init__.pyi
argus/_argus.cpython-313-arm-linux-gnueabihf.so
argus_temporal_logic-0.1.4.dist-info/RECORD
